autodynatrace/__init__.py
autodynatrace/log.py
autodynatrace/sdk.py
autodynatrace/wrappers/__init__.py
autodynatrace/wrappers/utils.py
autodynatrace/wrappers/aiohttp/__init__.py
autodynatrace/wrappers/aiohttp/wrapper.py
autodynatrace/wrappers/bottle/__init__.py
autodynatrace/wrappers/bottle/wrapper.py
autodynatrace/wrappers/celery/__init__.py
autodynatrace/wrappers/celery/wrapper.py
autodynatrace/wrappers/concurrent/__init__.py
autodynatrace/wrappers/concurrent/wrapper.py
autodynatrace/wrappers/confluent_kafka/__init__.py
autodynatrace/wrappers/confluent_kafka/wrapper.py
autodynatrace/wrappers/custom/__init__.py
autodynatrace/wrappers/custom/wrapper.py
autodynatrace/wrappers/cx_Oracle/__init__.py
autodynatrace/wrappers/cx_Oracle/wrapper.py
autodynatrace/wrappers/dbapi/__init__.py
autodynatrace/wrappers/django/__init__.py
autodynatrace/wrappers/django/apps.py
autodynatrace/wrappers/django/db.py
autodynatrace/wrappers/django/log.py
autodynatrace/wrappers/django/middlewares.py
autodynatrace/wrappers/django/utils.py
autodynatrace/wrappers/django/wrapper.py
autodynatrace/wrappers/django_outbox_pattern/__init__.py
autodynatrace/wrappers/django_outbox_pattern/consumer.py
autodynatrace/wrappers/django_outbox_pattern/publisher.py
autodynatrace/wrappers/django_outbox_pattern/wrapper.py
autodynatrace/wrappers/django_stomp/__init__.py
autodynatrace/wrappers/django_stomp/consumer.py
autodynatrace/wrappers/django_stomp/publisher.py
autodynatrace/wrappers/django_stomp/utils.py
autodynatrace/wrappers/django_stomp/wrapper.py
autodynatrace/wrappers/fastapi/__init__.py
autodynatrace/wrappers/fastapi/middleware.py
autodynatrace/wrappers/fastapi/wrapper.py
autodynatrace/wrappers/flask/__init__.py
autodynatrace/wrappers/flask/wrapper.py
autodynatrace/wrappers/grpc/__init__.py
autodynatrace/wrappers/grpc/wrapper.py
autodynatrace/wrappers/paramiko/__init__.py
autodynatrace/wrappers/paramiko/wrapper.py
autodynatrace/wrappers/pika/__init__.py
autodynatrace/wrappers/pika/wrapper.py
jsm_autodynatrace-1.1.1.dist-info/LICENSE
jsm_autodynatrace-1.1.1.dist-info/METADATA
jsm_autodynatrace-1.1.1.dist-info/WHEEL
jsm_autodynatrace-1.1.1.dist-info/entry_points.txt
jsm_autodynatrace-1.1.1.dist-info/top_level.txt
jsm_autodynatrace-1.1.1.dist-info/RECORD
